{
    "roles": {
        "cibernauta": {
            "name": "Cibernauta Responsable",
            "level": "Básico",
            "description": "Ciudadano digital comprometido con la detección y reporte de contenido sospechoso.",
            "permissions": {
                "analisis_ia": true,
                "validacion_humana": false,
                "historial": true,
                "mapa_desinfodemico": true,
                "mi_perfil": true,
                "centro_documentacion": true,
                "subir_contenido": true,
                "ver_resultados": true,
                "validar_casos": false,
                "editar_casos": false,
                "eliminar_casos": false,
                "comentar_casos": true,
                "ver_casos_propios": true,
                "ver_todos_casos": true,
                "estadisticas_personales": true,
                "analiticas_globales": false,
                "ver_lista_usuarios": false,
                "ver_logs": false,
                "config_perfil": true,
                "config_notificaciones": true,
                "gestionar_usuarios": false,
                "config_sistema": false,
                "config_motor_ia": false,
                "gestionar_etiquetas": false
            }
        },
        "epidemiologo": {
            "name": "Epidemiólogo AMI",
            "level": "Avanzado",
            "description": "Especialista capacitado para validar diagnósticos generados por IA y realizar análisis forense.",
            "permissions": {
                "analisis_ia": true,
                "validacion_humana": true,
                "historial": true,
                "mapa_desinfodemico": true,
                "mi_perfil": true,
                "centro_documentacion": true,
                "subir_contenido": true,
                "ver_resultados": true,
                "validar_casos": true,
                "editar_casos": true,
                "eliminar_casos": false,
                "comentar_casos": true,
                "ver_casos_propios": true,
                "ver_todos_casos": true,
                "estadisticas_personales": true,
                "analiticas_globales": "limitado",
                "ver_lista_usuarios": false,
                "ver_logs": false,
                "config_perfil": true,
                "config_notificaciones": true,
                "gestionar_usuarios": false,
                "config_sistema": false,
                "config_motor_ia": false,
                "gestionar_etiquetas": false
            }
        },
        "director": {
            "name": "Director Desinfodémico",
            "level": "Total",
            "description": "Autoridad técnica y estratégica que coordina la operación completa.",
            "permissions": {
                "analisis_ia": true,
                "validacion_humana": true,
                "historial": true,
                "mapa_desinfodemico": true,
                "mi_perfil": true,
                "centro_documentacion": true,
                "subir_contenido": true,
                "ver_resultados": true,
                "validar_casos": true,
                "editar_casos": true,
                "eliminar_casos": true,
                "comentar_casos": true,
                "ver_casos_propios": true,
                "ver_todos_casos": true,
                "estadisticas_personales": true,
                "analiticas_globales": true,
                "ver_lista_usuarios": true,
                "ver_logs": true,
                "config_perfil": true,
                "config_notificaciones": true,
                "gestionar_usuarios": true,
                "config_sistema": true,
                "config_motor_ia": true,
                "gestionar_etiquetas": true
            }
        }
    }
}